WhileDB/_WhileDB.pyd
WhileDB/_WhileDB.pyi
WhileDB/__init__.py
WhileDB-0.0.2.dist-info/METADATA
WhileDB-0.0.2.dist-info/WHEEL
WhileDB-0.0.2.dist-info/top_level.txt
WhileDB-0.0.2.dist-info/RECORD
